pytest_dsl_ui/__init__.py
pytest_dsl_ui/__main__.py
pytest_dsl_ui/core/__init__.py
pytest_dsl_ui/core/auth_manager.py
pytest_dsl_ui/core/browser_http_client.py
pytest_dsl_ui/core/browser_http_request.py
pytest_dsl_ui/core/browser_manager.py
pytest_dsl_ui/core/element_locator.py
pytest_dsl_ui/core/element_locator_improved.py
pytest_dsl_ui/core/page_context.py
pytest_dsl_ui/keywords/__init__.py
pytest_dsl_ui/keywords/assertion_keywords.py
pytest_dsl_ui/keywords/auth_keywords.py
pytest_dsl_ui/keywords/browser_http_keywords.py
pytest_dsl_ui/keywords/browser_keywords.py
pytest_dsl_ui/keywords/captcha_keywords.py
pytest_dsl_ui/keywords/capture_keywords.py
pytest_dsl_ui/keywords/clipboard_keywords.py
pytest_dsl_ui/keywords/download_keywords.py
pytest_dsl_ui/keywords/element_keywords.py
pytest_dsl_ui/keywords/element_keywords_extended.py
pytest_dsl_ui/keywords/navigation_keywords.py
pytest_dsl_ui/keywords/network_keywords.py
pytest_dsl_ui/utils/__init__.py
pytest_dsl_ui/utils/helpers.py
pytest_dsl_ui/utils/playwright_converter.py
pytest_dsl_ui-0.6.0.dist-info/METADATA
pytest_dsl_ui-0.6.0.dist-info/WHEEL
pytest_dsl_ui-0.6.0.dist-info/entry_points.txt
pytest_dsl_ui-0.6.0.dist-info/top_level.txt
pytest_dsl_ui-0.6.0.dist-info/RECORD
