Metadata-Version: 2.4
Name: pytest-dsl-ui
Version: 0.6.0
Summary: Playwright-based UI automation keywords for pytest-dsl framework
Author: Chen Shuanglin
License-Expression: MIT
Project-URL: Homepage, https://github.com/felix-1991/pytest-dsl-ui
Project-URL: Bug Tracker, https://github.com/felix-1991/pytest-dsl-ui/issues
Classifier: Framework :: Pytest
Classifier: Programming Language :: Python :: 3
Classifier: Programming Language :: Python :: 3.9
Classifier: Programming Language :: Python :: 3.10
Classifier: Programming Language :: Python :: 3.11
Classifier: Programming Language :: Python :: 3.12
Classifier: Operating System :: OS Independent
Requires-Python: >=3.9
Requires-Dist: pytest-dsl>=0.16.4
Requires-Dist: playwright>=1.40.0
Requires-Dist: allure-pytest>=2.9.0
Requires-Dist: Pillow>=9.0.0
Requires-Dist: ddddocr>=1.4.11
Requires-Dist: pyperclip>=1.8.0
Provides-Extra: dev
Requires-Dist: pytest>=7.0.0; extra == "dev"
Requires-Dist: pytest-cov>=4.0.0; extra == "dev"
Requires-Dist: black>=22.0.0; extra == "dev"
Requires-Dist: flake8>=5.0.0; extra == "dev"
